tfbm/TFBM.py
tfbm/__init__.py
tfbm/data_scaling.py
tfbm/distance.py
tfbm/image_proc.py
tfbm/load_data.py
tfbm/main.py
tfbm/maxima.py
tfbm/neighbourhood.py
tfbm/structs.py
tfbm-0.0.2.dist-info/LICENSE.txt
tfbm-0.0.2.dist-info/METADATA
tfbm-0.0.2.dist-info/WHEEL
tfbm-0.0.2.dist-info/top_level.txt
tfbm-0.0.2.dist-info/RECORD
