Metadata-Version: 2.1
Name: tfbm
Version: 0.0.2
Summary: The Time-Frequency Breakdown Method (TFBM) was developed for the detection of brain oscillations in time-frequency representations (such as spectrograms obtained from the Fourier Transform).
Home-page: https://https://github.com/ArdeleanRichard/Time-Frequency-Breakdown-Method
Author: Eugen-Richard Ardelean
Author-email: ardeleaneugenrichard@gmail.com
License: MIT
Classifier: License :: OSI Approved :: MIT License
Classifier: Programming Language :: Python :: 3.7
Classifier: Operating System :: OS Independent
Requires-Python: >=3.7
License-File: LICENSE.txt
Requires-Dist: numpy
Requires-Dist: scikit-learn
Provides-Extra: dev
Requires-Dist: twine >=4.0.2 ; extra == 'dev'
